mjolnir_arq/__init__.py
mjolnir_arq/module.py
mjolnir_arq/backend_hexagonal/.env.local
mjolnir_arq/backend_hexagonal/.env.pc
mjolnir_arq/backend_hexagonal/.env.production
mjolnir_arq/backend_hexagonal/.env.qa
mjolnir_arq/backend_hexagonal/.gitignore
mjolnir_arq/backend_hexagonal/Dockerfile.local
mjolnir_arq/backend_hexagonal/Dockerfile.qa
mjolnir_arq/backend_hexagonal/README.md
mjolnir_arq/backend_hexagonal/__init__.py
mjolnir_arq/backend_hexagonal/docker-compose.local.yml
mjolnir_arq/backend_hexagonal/docker-compose.qa.yml
mjolnir_arq/backend_hexagonal/main.py
mjolnir_arq/backend_hexagonal/pipfiles.txt
mjolnir_arq/backend_hexagonal/migrations/changelog-v1.sql
mjolnir_arq/backend_hexagonal/src/__init__.py
mjolnir_arq/backend_hexagonal/src/core/__init__.py
mjolnir_arq/backend_hexagonal/src/core/config.py
mjolnir_arq/backend_hexagonal/src/core/classes/__init__.py
mjolnir_arq/backend_hexagonal/src/core/classes/api_client.py
mjolnir_arq/backend_hexagonal/src/core/classes/async_message.py
mjolnir_arq/backend_hexagonal/src/core/classes/bearer.py
mjolnir_arq/backend_hexagonal/src/core/classes/password.py
mjolnir_arq/backend_hexagonal/src/core/classes/token.py
mjolnir_arq/backend_hexagonal/src/core/enums/__init__.py
mjolnir_arq/backend_hexagonal/src/core/enums/condition_type.py
mjolnir_arq/backend_hexagonal/src/core/enums/context.py
mjolnir_arq/backend_hexagonal/src/core/enums/keys_message.py
mjolnir_arq/backend_hexagonal/src/core/enums/language.py
mjolnir_arq/backend_hexagonal/src/core/enums/layer.py
mjolnir_arq/backend_hexagonal/src/core/enums/message_type.py
mjolnir_arq/backend_hexagonal/src/core/enums/notification_type.py
mjolnir_arq/backend_hexagonal/src/core/enums/permission_type.py
mjolnir_arq/backend_hexagonal/src/core/enums/response_type.py
mjolnir_arq/backend_hexagonal/src/core/methods/__init__.py
mjolnir_arq/backend_hexagonal/src/core/methods/apply_memory_filters.py
mjolnir_arq/backend_hexagonal/src/core/methods/build_alias_map.py
mjolnir_arq-0.0.43.dist-info/LICENSE
mjolnir_arq-0.0.43.dist-info/METADATA
mjolnir_arq-0.0.43.dist-info/WHEEL
mjolnir_arq-0.0.43.dist-info/entry_points.txt
mjolnir_arq-0.0.43.dist-info/top_level.txt
mjolnir_arq-0.0.43.dist-info/RECORD
